random_algorithm/__init__.py
random_algorithm/random_algorithm.py
random_algorithm/wordlist.txt
random_algorithm/words_list.py
random_algorithm-1.1.0.dist-info/LICENSE
random_algorithm-1.1.0.dist-info/METADATA
random_algorithm-1.1.0.dist-info/WHEEL
random_algorithm-1.1.0.dist-info/top_level.txt
random_algorithm-1.1.0.dist-info/RECORD
