Metadata-Version: 2.1
Name: random_algorithm
Version: 1.1.0
Summary: A random number generator based on shuffled English words, their ASCII values, and the current epoch time to create highly randomized outputs
Home-page: https://github.com/EDM115/random-algorithm
Author: EDM115
Author-email: EDM115 <dev@edm115.eu.org>
License: MIT License
Project-URL: Homepage, https://github.com/EDM115/random-algorithm
Project-URL: Bug Tracker, https://github.com/EDM115/random-algorithm/issues
Project-URL: Funding, https://github.com/EDM115#support-me-
Keywords: random,number,generator,ascii,english,algorithm
Classifier: Development Status :: 5 - Production/Stable
Classifier: Intended Audience :: Developers
Classifier: Topic :: Software Development
Classifier: License :: OSI Approved :: MIT License
Classifier: Programming Language :: Python :: 2
Classifier: Programming Language :: Python :: 3
License-File: LICENSE
